LordPath/__init__.py
LordPath/dataset.py
LordPath/descriptors.py
LordPath/filefolderclass.py
LordPath/opener/__init__.py
LordPath/opener/base.py
LordPath/opener/json.py
LordPath/opener/pickle.py
LordPath/opener/toml.py
LordPath/opener/xml.py
LordPath/opener/yaml.py
LordPath-2023.7.9.dist-info/METADATA
LordPath-2023.7.9.dist-info/WHEEL
LordPath-2023.7.9.dist-info/top_level.txt
LordPath-2023.7.9.dist-info/RECORD
