Metadata-Version: 2.1
Name: LordPath
Version: 2023.7.9
Summary: File Manager Helping Module base on Pathlib
Author-email: lordbex <lordibex@protonmail.com>
Maintainer-email: lordbex <lordibex@protonmail.com>
Project-URL: homepage, https://github.com/LordBex
Project-URL: repository, https://github.com/LordBex
Requires-Python: >=3.10
Requires-Dist: regex
Requires-Dist: pyyaml
Requires-Dist: LordUtils
